CHANGELOG.rst
MANIFEST.in
README.rst
setup.py
tox.ini
readinglist/__init__.py
readinglist.egg-info/PKG-INFO
readinglist.egg-info/SOURCES.txt
readinglist.egg-info/dependency_links.txt
readinglist.egg-info/entry_points.txt
readinglist.egg-info/not-zip-safe
readinglist.egg-info/requires.txt
readinglist.egg-info/top_level.txt
readinglist/tests/__init__.py
readinglist/tests/support.py
readinglist/tests/test_article_schema.py
readinglist/tests/test_initialization.py
readinglist/tests/test_views_article.py
readinglist/tests/test_views_hello.py
readinglist/views/__init__.py
readinglist/views/article.py